Metadata-Version: 2.1
Name: odoo-addon-base-rest-datamodel
Version: 16.0.1.0.0.5
Summary: Datamodel binding for base_rest
Home-page: https://github.com/OCA/rest-framework
Author: ACSONE SA/NV,Odoo Community Association (OCA)
Author-email: support@odoo-community.org
License: LGPL-3
Platform: UNKNOWN
Classifier: Programming Language :: Python
Classifier: Framework :: Odoo
Classifier: Framework :: Odoo :: 16.0
Classifier: License :: OSI Approved :: GNU Lesser General Public License v3 (LGPLv3)
Requires-Python: >=3.10
Requires-Dist: apispec >=4.0.0
Requires-Dist: marshmallow
Requires-Dist: odoo-addon-base-rest <16.1dev,>=16.0dev
Requires-Dist: odoo-addon-datamodel <16.1dev,>=16.0dev
Requires-Dist: odoo <16.1dev,>=16.0a
